shawlTrie/__init__.py
shawlTrie/__main__.py
shawlTrie/cli.py
shawlTrie-0.0.1.dist-info/LICENSE
shawlTrie-0.0.1.dist-info/METADATA
shawlTrie-0.0.1.dist-info/WHEEL
shawlTrie-0.0.1.dist-info/entry_points.txt
shawlTrie-0.0.1.dist-info/top_level.txt
shawlTrie-0.0.1.dist-info/RECORD
