Metadata-Version: 2.1
Name: shawlTrie
Version: 0.0.1
Summary: UNKNOWN
Home-page: UNKNOWN
License: UNKNOWN
Platform: UNKNOWN
Requires-Dist: shawlTrie
Requires-Dist: pymongo
